expectise/__init__.py
expectise/exceptions/__init__.py
expectise/exceptions/environment_error.py
expectise/exceptions/expectation_error.py
expectise/hooks/__init__.py
expectise/hooks/disable_mock.py
expectise/hooks/mock.py
expectise/hooks/mock_if.py
expectise/hooks/tear_down.py
expectise/lib/expect.py
expectise/lib/expectations.py
expectise/lib/marker.py
expectise/lib/mock.py
expectise/lib/mock_instance.py
expectise/lib/session.py
expectise/models/__init__.py
expectise/models/decoration.py
expectise/models/kallable.py
expectise/models/lifespan.py
expectise/models/trigger.py
expectise/utils/diff.py
expectise-2.0.2.dist-info/METADATA
expectise-2.0.2.dist-info/WHEEL
expectise-2.0.2.dist-info/RECORD
