Metadata-Version: 2.3
Name: expectise
Version: 2.0.2
Summary: Mocking API and function calls in Python - inspired by Ruby's RSpec-Mocks.
Keywords: python,testing,mocking,unit,tests
Author: tcassou
Requires-Python: >=3.10,<4.0
Classifier: Intended Audience :: Developers
Classifier: Programming Language :: Python
Classifier: Programming Language :: Python :: 3
Classifier: Programming Language :: Python :: 3.10
Classifier: Programming Language :: Python :: 3.11
Classifier: Programming Language :: Python :: 3.12
Classifier: Programming Language :: Python :: 3.13
Classifier: Topic :: Software Development :: Testing
Classifier: Topic :: Software Development :: Testing :: Mocking
Project-URL: Homepage, https://github.com/tcassou/expectise
Project-URL: Repository, https://github.com/tcassou/expectise
